bdax/__init__.py
bdax/blackjaxsampling.py
bdax/flaxtraining.py
bdax/jaxpymc.py
bdax-0.1.4.dist-info/METADATA
bdax-0.1.4.dist-info/WHEEL
bdax-0.1.4.dist-info/RECORD
